setup.py
omni2re/__init__.py
omni2re/account.py
omni2re/elements.py
omni2re/query.py
omni2re/reports.py
omni2re/utils.py
omni2re.egg-info/PKG-INFO
omni2re.egg-info/SOURCES.txt
omni2re.egg-info/dependency_links.txt
omni2re.egg-info/requires.txt
omni2re.egg-info/top_level.txt