Metadata-Version: 1.1
Name: omni2re
Version: 0.4.2
Summary: A wrapper for the Adobe Omniture and SiteCatalyst web analytics API.
Home-page: http://github.com/colemanja91/python-omniture/
Author: Stijn Debrouwere, Jeremiah Coleman
Author-email: stijn@stdout.be, colemanja91@gmail.com
License: MIT
Download-URL: http://www.github.com/colemanja91/python-omniture/tarball/master
Keywords: data analytics api wrapper adobe
Platform: UNKNOWN
Classifier: Development Status :: 4 - Beta
Classifier: Intended Audience :: Developers
Classifier: License :: OSI Approved :: MIT License
Classifier: Operating System :: OS Independent
Classifier: Programming Language :: Python
Classifier: Topic :: Scientific/Engineering :: Information Analysis
